Metadata-Version: 2.4
Name: iflow-mcp_manim-mcp-server
Version: 0.1.0
Summary: MCP server that executes Manim animation code and returns the generated video
Author-email: abhiemj <abhiemj@example.com>
License: MIT License
Project-URL: Homepage, https://github.com/iflow-mcp/manim-mcp-server
Project-URL: Repository, https://github.com/iflow-mcp/manim-mcp-server
Requires-Python: >=3.10
License-File: LICENSE.txt
Requires-Dist: mcp>=1.0.0
Requires-Dist: manim>=0.18.0
Dynamic: license-file
